hgd/__init__.py
hgd/_download.py
hgd/config.py
hgd/inference.py
hgd/model.py
hgd/py.typed
hgd/video.py
hgd-0.4.0.dist-info/LICENSE
hgd-0.4.0.dist-info/METADATA
hgd-0.4.0.dist-info/WHEEL
hgd-0.4.0.dist-info/top_level.txt
hgd-0.4.0.dist-info/RECORD
