Metadata-Version: 2.1
Name: hgd
Version: 0.4.0
Summary: Detection and classification of head gestures in videos
Home-page: https://github.com/bhky/head-gesture-detection
Author: attr: hgd.__author__
Author-email: xtorch501@gmail.com
License: UNKNOWN
Platform: UNKNOWN
Classifier: Programming Language :: Python :: 3
Classifier: License :: OSI Approved :: MIT License
Classifier: Operating System :: OS Independent
Requires-Python: >=3.8
License-File: LICENSE
Requires-Dist: gdown (>=4.2.0)
Requires-Dist: mediapipe (>=0.8.9.1)
Requires-Dist: numpy (>=1.22.0)
Requires-Dist: opencv-python (>=4.0.0.0)
Requires-Dist: tensorflow (>=2.7.0)
